gdnan.py
gdnan-1.0.0.dist-info/LICENSE
gdnan-1.0.0.dist-info/METADATA
gdnan-1.0.0.dist-info/WHEEL
gdnan-1.0.0.dist-info/top_level.txt
gdnan-1.0.0.dist-info/RECORD
