Metadata-Version: 2.1
Name: gdnan
Version: 1.0.0
Summary: Google Drive API wrapper written in python 3.
Home-page: https://github.com/viperadnan-git/gdnan
Author: Adnan Ahmad
Author-email: viperadnan@gmail.com
License: UNKNOWN
Download-URL: https://github.com/viperadnan-git/gdnan/archive/v1.0.0.tar.gz
Keywords: GoogleDrive,GoogleDriveAPI,GDriveAPI,Google,Drive,Wrapper,GDrive
Platform: UNKNOWN
Classifier: Programming Language :: Python :: 3
Classifier: Programming Language :: Python :: 3.6
Classifier: Programming Language :: Python :: 3.9
Classifier: License :: OSI Approved :: GNU General Public License v3 or later (GPLv3+)
Classifier: Operating System :: OS Independent
Requires-Python: >=3.6
Requires-Dist: google-api-python-client (<2.0.0,>=1.12.8)
Requires-Dist: google-auth-httplib2 (<0.1.0,>=0.0.3)
Requires-Dist: oauth2client
Requires-Dist: tenacity
